pywxclient/__init__.py
pywxclient/utils.py
pywxclient/contrib/__init__.py
pywxclient/contrib/file.py
pywxclient/core/__init__.py
pywxclient/core/api.py
pywxclient/core/client.py
pywxclient/core/contact.py
pywxclient/core/exception.py
pywxclient/core/message.py
pywxclient/core/session.py
pywxclient-0.1.2.dist-info/DESCRIPTION.rst
pywxclient-0.1.2.dist-info/METADATA
pywxclient-0.1.2.dist-info/RECORD
pywxclient-0.1.2.dist-info/WHEEL
pywxclient-0.1.2.dist-info/entry_points.txt
pywxclient-0.1.2.dist-info/metadata.json
pywxclient-0.1.2.dist-info/top_level.txt
pywxclient-0.1.2.dist-info/zip-safe
