Metadata-Version: 2.0
Name: pywxclient
Version: 0.1.2
Summary: A simple WeChat client written in Python.
Home-page: https://github.com/justdoit0823/pywxclient
Author: justdoit0823
Author-email: justdoit920823@gamil.com
License: Apache 2.0
Keywords: WeChat Python HTTP
Platform: UNKNOWN
Classifier: Development Status :: 5 - Production/Stable
Classifier: Intended Audience :: Developers
Classifier: License :: OSI Approved :: Apache Software License
Classifier: Programming Language :: Python :: 3
Classifier: Programming Language :: Python :: 3.3
Classifier: Programming Language :: Python :: 3.4
Classifier: Programming Language :: Python :: 3.5
Classifier: Programming Language :: Python :: 3.6
Classifier: Programming Language :: Python :: Implementation :: CPython
Requires-Dist: requests (>=2.10.0)
